{
  "decision_reason": "오케스트레이터가 Lenny Team owner를 세우고, 동시에 할 수 있는 실무는 병렬로 시작하되 통합/최종 판단은 순서대로 진행하도록 판단했습니다.",
  "execution_mode": "mixed",
  "mode": "team_dispatch",
  "needs_assignment_review": true,
  "parallel_reason": "서로 기다리지 않아도 되는 실무 worker는 같은 실행 그룹에서 동시에 시작합니다.",
  "parallelization": {
    "considered": true,
    "decision": "mixed",
    "execution_groups": [
      {
        "id": "parallel-1",
        "mode": "parallel",
        "reason": "증거 수집과 주 구현은 서로 기다리지 않아도 되므로 동시에 시작합니다."
      },
      {
        "depends_on": [
          "parallel-1"
        ],
        "id": "serial-integration",
        "mode": "serial",
        "reason": "통합과 수정은 선행 worker 결과가 필요합니다."
      },
      {
        "depends_on": [
          "serial-integration"
        ],
        "id": "serial-release",
        "mode": "serial",
        "reason": "최종 판단은 통합 결과 뒤에 진행합니다."
      }
    ],
    "reason": "오케스트레이터가 Lenny Team owner를 세우고, 동시에 할 수 있는 실무는 병렬로 시작하되 통합/최종 판단은 순서대로 진행하도록 판단했습니다.",
    "worker_count": 4
  },
  "primary_owner": "ai-ops-expert",
  "reason": "오케스트레이터가 Lenny Team owner를 세우고, 동시에 할 수 있는 실무는 병렬로 시작하되 통합/최종 판단은 순서대로 진행하도록 판단했습니다.",
  "resolved_tier": "tier3",
  "serial_reason": null,
  "solo_reason": null,
  "tier": "tier3"
}
